opendatapy/__init__.py
opendatapy/datakit.py
opendatapy/helpers.py
opendatapy/py.typed
opendatapy/resources.py
opendatapy-0.1.2.dist-info/LICENSE
opendatapy-0.1.2.dist-info/METADATA
opendatapy-0.1.2.dist-info/WHEEL
opendatapy-0.1.2.dist-info/top_level.txt
opendatapy-0.1.2.dist-info/RECORD
